simplepush/__init__.py
simplepush/simplepush.py
simplepush-2.2.4.dist-info/licenses/LICENSE.txt
simplepush-2.2.4.dist-info/METADATA
simplepush-2.2.4.dist-info/WHEEL
simplepush-2.2.4.dist-info/top_level.txt
simplepush-2.2.4.dist-info/RECORD
