Metadata-Version: 2.4
Name: simplepush
Version: 2.2.4
Summary: Simplepush Python Library
Author-email: Timm Schaeuble <contact@simplepush.io>
Project-URL: Homepage, https://github.com/simplepush/simplepush-python
Project-URL: Bug Tracker, https://github.com/simplepush/simplepush-python/issues
Classifier: Programming Language :: Python :: 3
Classifier: License :: OSI Approved :: MIT License
Classifier: Operating System :: OS Independent
License-File: LICENSE.txt
Requires-Dist: requests
Requires-Dist: cryptography
Requires-Dist: aiohttp
Dynamic: license-file
